gcnn_dmri/__init__.py
gcnn_dmri/cutnifti.py
gcnn_dmri/dataGrab.py
gcnn_dmri/diffusion.py
gcnn_dmri/dihedral12.py
gcnn_dmri/example_scripts/__init__.py
gcnn_dmri/example_scripts/niceData.py
gcnn_dmri/example_scripts/predicting_script.py
gcnn_dmri/example_scripts/training_script.py
gcnn_dmri/gPyTorch.py
gcnn_dmri/geodesic.py
gcnn_dmri/icosahedron.py
gcnn_dmri/metrics.py
gcnn_dmri/predictingScalar.py
gcnn_dmri/preprocessing.py
gcnn_dmri/trainingScalars.py
gcnn_dmri-0.1.0.dist-info/WHEEL
gcnn_dmri-0.1.0.dist-info/METADATA
gcnn_dmri-0.1.0.dist-info/RECORD
