Metadata-Version: 2.1
Name: gcnn-dmri
Version: 0.1.0
Summary: Graph-equivariant CNNs for diffusion MRI
Home-page: https://akhanf.github.io/gcnn_dmri
License: MIT
Author: Uzair Hussain
Requires-Python: >=3.8,<3.12
Classifier: Development Status :: 4 - Beta
Classifier: Intended Audience :: Developers
Classifier: License :: OSI Approved :: MIT License
Classifier: Operating System :: OS Independent
Classifier: Programming Language :: Python
Classifier: Programming Language :: Python :: 3
Classifier: Programming Language :: Python :: 3.10
Classifier: Programming Language :: Python :: 3.7
Classifier: Programming Language :: Python :: 3.8
Classifier: Programming Language :: Python :: 3.9
Classifier: Topic :: Software Development :: Libraries :: Python Modules
Classifier: Typing :: Typed
Requires-Dist: antiprism-python (>=0.1.3,<0.2.0)
Requires-Dist: dipy (>=1.5.0,<2.0.0)
Requires-Dist: matplotlib (>=3.6.0,<4.0.0)
Requires-Dist: nibabel (>=4.0.2,<5.0.0)
Requires-Dist: numpy (>=1.23.0,<2.0.0)
Requires-Dist: scipy (>=1.9.1,<2.0.0)
Requires-Dist: stripy (>=2.1.0,<3.0.0)
Requires-Dist: torch (>=1.7.1,<2.0.0)
Project-URL: Documentation, https://akhanf.github.io/gcnn_dmri
Project-URL: Repository, https://github.com/akhanf/gcnn_dmri
